[
  {
    "id": "health_potion",
    "name": "Pocao de Vida",
    "type": "consumable",
    "description": "Restitui 60 pontos de Saude.",
    "heal_hp": 60,
    "value": 25
  },
  {
    "id": "spirit_elixir",
    "name": "Elixir de Espirito",
    "type": "consumable",
    "description": "Restitui 30 pontos de Espirito.",
    "heal_sp": 30,
    "value": 30
  },
  {
    "id": "battle_bread",
    "name": "Pao de Peleja",
    "type": "consumable",
    "description": "Restitui 20 pontos de Saude.",
    "heal_hp": 20,
    "value": 8
  },
  {
    "id": "merchant_ring",
    "name": "Anel do Mercador",
    "type": "accessory",
    "description": "Anel singelo dado como paga por servico bem cumprido.",
    "value": 150
  },
  {
    "id": "manual_corte_da_sonda",
    "name": "Pergaminho do Corte da Sonda",
    "type": "manual_skill",
    "school": "Escola da Barra de Lisboa",
    "quality": "green",
    "min_level": 2,
    "teach_skill": "corte_da_sonda",
    "description": "Ensina um corte seco e profundo, medido como sonda de fundo.",
    "value": 80
  },
  {
    "id": "manual_brisa_da_alvorada",
    "name": "Livro da Brisa da Alvorada",
    "type": "manual_passive",
    "school": "Escola da Barra de Lisboa",
    "quality": "white",
    "min_level": 2,
    "teach_passive": "brisa_da_alvorada",
    "description": "Compendio de respiracao e passo leve para quem sai ao mar com a primeira luz.",
    "value": 65
  },
  {
    "id": "manual_onda_em_arco",
    "name": "Pergaminho da Onda em Arco",
    "type": "manual_skill",
    "school": "Casa dos Pilotos do Douro",
    "quality": "blue",
    "min_level": 3,
    "teach_skill": "onda_em_arco",
    "description": "Doutrina do golpe amplo que varre o flanco como agua torcida por rocha.",
    "value": 130
  },
  {
    "id": "manual_pele_salgada",
    "name": "Livro da Pele Salgada",
    "type": "manual_passive",
    "school": "Casa dos Pilotos do Douro",
    "quality": "blue",
    "min_level": 3,
    "teach_passive": "pele_salgada",
    "description": "Caderno de vigias e disciplina corporal para endurecer nervo, osso e pulso.",
    "value": 120
  },
  {
    "id": "manual_folego_da_estiva",
    "name": "Livro do Folego da Estiva",
    "type": "manual_passive",
    "school": "Casa dos Pilotos do Douro",
    "quality": "blue",
    "min_level": 4,
    "teach_passive": "folego_da_estiva",
    "description": "Notas de faina do cais que ensinam a tomar Espirito do ritmo da estiva e da queda do adversario.",
    "value": 145
  },
  {
    "id": "manual_clarim_do_farol",
    "name": "Pergaminho do Clarim do Farol",
    "type": "manual_skill",
    "school": "Irmandade do Farol de Sagres",
    "quality": "purple",
    "min_level": 4,
    "teach_skill": "clarim_do_farol",
    "description": "Arte rara que quebra o animo do adversario com voz, luz e mar.",
    "value": 220
  },
  {
    "id": "manual_olho_da_estrela_polar",
    "name": "Livro do Olho da Estrela Polar",
    "type": "manual_passive",
    "school": "Irmandade do Farol de Sagres",
    "quality": "purple",
    "min_level": 4,
    "teach_passive": "olho_da_estrela_polar",
    "description": "Tratado de observacao nocturna e rumo firme, proprio de pilotos de alta agua.",
    "value": 210
  },
  {
    "id": "manual_circulo_da_almenara",
    "name": "Pergaminho do Circulo da Almenara",
    "type": "manual_skill",
    "school": "Irmandade do Farol de Sagres",
    "quality": "purple",
    "min_level": 5,
    "teach_skill": "circulo_da_almenara",
    "description": "Arte do lume de aviso, ensinada aos que sabem castigar um flanco inteiro a partir da altura.",
    "value": 260
  },
  {
    "id": "manual_vigia_do_promontorio",
    "name": "Livro da Vigia do Promontorio",
    "type": "manual_passive",
    "school": "Irmandade do Farol de Sagres",
    "quality": "purple",
    "min_level": 5,
    "teach_passive": "vigia_do_promontorio",
    "description": "Livro guardado junto ao farol, para quem aprende a suster a altura e nao ceder a Atordoamento.",
    "value": 240
  },
  {
    "id": "manual_roda_do_astrolabio",
    "name": "Pergaminho da Roda do Astrolabio",
    "type": "manual_skill",
    "school": "Circulo da Esfera de Tomar",
    "quality": "gold",
    "min_level": 6,
    "teach_skill": "roda_do_astrolabio",
    "description": "Arte de compasso e esfera que mede o inimigo em redor do centro marcado.",
    "value": 320
  },
  {
    "id": "manual_regra_da_charola",
    "name": "Livro da Regra da Charola",
    "type": "manual_passive",
    "school": "Circulo da Esfera de Tomar",
    "quality": "gold",
    "min_level": 6,
    "teach_passive": "regra_da_charola",
    "description": "Doutrina de centro, silencio e compasso, guardada pelos letrados de Tomar.",
    "value": 310
  },
  {
    "id": "manual_linha_do_zodiaco",
    "name": "Pergaminho da Linha do Zodiaco",
    "type": "manual_skill",
    "school": "Circulo da Esfera de Tomar",
    "quality": "gold",
    "min_level": 7,
    "teach_skill": "linha_do_zodiaco",
    "description": "Traza uma linha de golpe tao direita como carta celeste lavrada a compasso.",
    "value": 360
  },
  {
    "id": "manual_corte_do_estreito",
    "name": "Pergaminho do Corte do Estreito",
    "type": "manual_skill",
    "school": "Guarda do Estreito de Ceuta",
    "quality": "red",
    "min_level": 8,
    "teach_skill": "corte_do_estreito",
    "description": "Golpe severo de quem aprendeu a fechar passagem e ferro no estreito.",
    "value": 430
  },
  {
    "id": "manual_guarda_da_alfandega",
    "name": "Livro da Guarda da Alfandega",
    "type": "manual_passive",
    "school": "Guarda do Estreito de Ceuta",
    "quality": "red",
    "min_level": 8,
    "teach_passive": "guarda_da_alfandega",
    "description": "Doutrina de muralha, ponte e porto, para quem segura passagem contra mar e ferro.",
    "value": 410
  },
  {
    "id": "manual_mare_do_levante",
    "name": "Pergaminho da Mare do Levante",
    "type": "manual_skill",
    "school": "Guarda do Estreito de Ceuta",
    "quality": "red",
    "min_level": 9,
    "teach_skill": "mare_do_levante",
    "description": "Arte do vento oriental e da vaga curta, pronta para quebrar roda de inimigos.",
    "value": 470
  },
  {
    "id": "manual_corrente_da_barra",
    "name": "Pergaminho da Corrente da Barra",
    "type": "manual_skill",
    "school": "Escola da Barra de Lisboa",
    "quality": "white",
    "min_level": 1,
    "teach_skill": "corrente_da_barra",
    "description": "Doutrina simples do golpe que segue a mare da barra.",
    "value": 60
  },
  {
    "id": "manual_mar_de_vidro",
    "name": "Pergaminho do Mar de Vidro",
    "type": "manual_skill",
    "school": "Escola da Barra de Lisboa",
    "quality": "green",
    "min_level": 3,
    "teach_skill": "mar_de_vidro",
    "description": "Arte fria e medida, feita para quebrar o tino do adversario.",
    "value": 120
  },
  {
    "id": "manual_firmeza_da_pedra",
    "name": "Livro da Firmeza da Pedra",
    "type": "manual_passive",
    "school": "Escola da Barra de Lisboa",
    "quality": "green",
    "min_level": 2,
    "teach_passive": "firmeza_da_pedra",
    "description": "Licao de barra e rochedo para quem deseja manter-se firme sob vaga curta.",
    "value": 110
  },
  {
    "id": "manual_cabo_da_ribeira",
    "name": "Pergaminho do Cabo da Ribeira",
    "type": "manual_skill",
    "school": "Casa dos Pilotos do Douro",
    "quality": "green",
    "min_level": 3,
    "teach_skill": "cabo_da_ribeira",
    "description": "Doutrina de cabo e ribeira, que prende e rasga com tino.",
    "value": 120
  },
  {
    "id": "manual_pulso_da_ribeira",
    "name": "Livro do Pulso da Ribeira",
    "type": "manual_passive",
    "school": "Casa dos Pilotos do Douro",
    "quality": "green",
    "min_level": 3,
    "teach_passive": "pulso_da_ribeira",
    "description": "Ensina a recuperar Espirito quando um inimigo cai ao convés.",
    "value": 120
  },
  {
    "id": "manual_quebra_mar_do_douro",
    "name": "Pergaminho do Quebra-Mar do Douro",
    "type": "manual_skill",
    "school": "Casa dos Pilotos do Douro",
    "quality": "blue",
    "min_level": 4,
    "teach_skill": "quebra_mar_do_douro",
    "description": "Arte larga dos pilotos do norte, feita para varrer o flanco do inimigo.",
    "value": 160
  },
  {
    "id": "manual_ombros_do_cais",
    "name": "Livro dos Ombros do Cais",
    "type": "manual_passive",
    "school": "Casa dos Pilotos do Douro",
    "quality": "blue",
    "min_level": 4,
    "teach_passive": "ombros_do_cais",
    "description": "Ensina a sustentar o peso do cais e a nao ceder com agua pelas canelas.",
    "value": 160
  },
  {
    "id": "manual_luz_do_cabo",
    "name": "Pergaminho da Luz do Cabo",
    "type": "manual_skill",
    "school": "Irmandade do Farol de Sagres",
    "quality": "purple",
    "min_level": 5,
    "teach_skill": "luz_do_cabo",
    "description": "Arte do farol que reacende o Espirito e guia a mao.",
    "value": 220
  },
  {
    "id": "manual_grito_da_vigia",
    "name": "Pergaminho do Grito da Vigia",
    "type": "manual_skill",
    "school": "Irmandade do Farol de Sagres",
    "quality": "purple",
    "min_level": 5,
    "teach_skill": "grito_da_vigia",
    "description": "Brado de vigia que quebra o passo de quem sobe ao promontorio.",
    "value": 230
  },
  {
    "id": "manual_chama_do_farol",
    "name": "Livro da Chama do Farol",
    "type": "manual_passive",
    "school": "Irmandade do Farol de Sagres",
    "quality": "purple",
    "min_level": 5,
    "teach_passive": "chama_do_farol",
    "description": "Ensina a tomar altura e a manter a cabeca firme contra o atordoamento.",
    "value": 230
  },
  {
    "id": "manual_compasso_da_charola",
    "name": "Pergaminho do Compasso da Charola",
    "type": "manual_skill",
    "school": "Circulo da Esfera de Tomar",
    "quality": "gold",
    "min_level": 7,
    "teach_skill": "compasso_da_charola",
    "description": "Arte dourada que roda sobre o centro marcado e fere a roda inimiga.",
    "value": 340
  },
  {
    "id": "manual_selo_do_nabao",
    "name": "Pergaminho do Selo do Nabao",
    "type": "manual_skill",
    "school": "Circulo da Esfera de Tomar",
    "quality": "gold",
    "min_level": 8,
    "teach_skill": "selo_do_nabao",
    "description": "Selo de agua e pedra para quebrar o tino do adversario.",
    "value": 360
  },
  {
    "id": "manual_silencio_do_claustro",
    "name": "Livro do Silencio do Claustro",
    "type": "manual_passive",
    "school": "Circulo da Esfera de Tomar",
    "quality": "gold",
    "min_level": 7,
    "teach_passive": "silencio_do_claustro",
    "description": "Doutrina de silencio e folego para quem aprende o centro de Tomar.",
    "value": 330
  },
  {
    "id": "manual_passo_da_muralha",
    "name": "Pergaminho do Passo da Muralha",
    "type": "manual_skill",
    "school": "Guarda do Estreito de Ceuta",
    "quality": "red",
    "min_level": 9,
    "teach_skill": "passo_da_muralha",
    "description": "Arte vermelha que firma o passo e fecha a guarda no estreito.",
    "value": 460
  },
  {
    "id": "manual_ferro_da_ponte",
    "name": "Pergaminho do Ferro da Ponte",
    "type": "manual_skill",
    "school": "Guarda do Estreito de Ceuta",
    "quality": "red",
    "min_level": 10,
    "teach_skill": "ferro_da_ponte",
    "description": "Golpe de ponte e ferro que abre caminho no estreito.",
    "value": 500
  },
  {
    "id": "manual_muralha_do_estreito",
    "name": "Livro da Muralha do Estreito",
    "type": "manual_passive",
    "school": "Guarda do Estreito de Ceuta",
    "quality": "red",
    "min_level": 9,
    "teach_passive": "muralha_do_estreito",
    "description": "Ensina a fazer do corpo muralha e a sofrer menos com agua e ferro.",
    "value": 440
  },
  {
    "id": "mantimentos_de_bordo",
    "name": "Mantimentos de Bordo",
    "type": "ocean_supply",
    "description": "Sacos de biscoito, agua e sal para reabastecer a nau.",
    "supplies_gain": 35,
    "value": 60
  },
  {
    "id": "calafeto_de_mestra",
    "name": "Calafeto de Mestra",
    "type": "ocean_repair",
    "description": "Madeira seca, breu e ferro para reforcar o casco.",
    "ship_gain": 25,
    "value": 80
  }
]
